Metadata-Version: 1.1
Name: libpythonpro-fnsouza
Version: 0.2
Summary: Módulo para exemplificar construção de projetos Python no curso PyTools
Home-page: https://github.com/fnscoder/libpythonpro-fnsouza
Author: Felipe N Souza
Author-email: fnsouza.me@gmail.com
License: GNU AFFERO GENERAL PUBLIC LICENSE
Platform: UNKNOWN
Classifier: Development Status :: 2 - Pre-Alpha
Classifier: Environment :: Console
Classifier: Intended Audience :: Developers
Classifier: License :: OSI Approved :: GNU Affero General Public License v3 or later (AGPLv3+)
Classifier: Operating System :: OS Independent
Classifier: Programming Language :: Python
Classifier: Programming Language :: Python :: 3.6
Classifier: Framework :: Pytest
